problem5/sequence.detector.module.v
module sequence_detector(
    input wire clk,
    input wire reset,       // Reset signal
    input wire in_bit,
    output reg seq_detected 
);
    // State encoding
    parameter S0 = 3'b000;
    parameter S1 = 3'b001;
    parameter S2 = 3'b010;
    parameter S3 = 3'b011;
    parameter S4 = 3'b100;
    parameter S5 = 3'b101;
    parameter S6 = 3'b110;
    parameter S7 = 3'b111;

    reg [2:0] current_state, next_state;

    // Initialize the state machine 
    initial begin
        current_state = S0;
        next_state = S0;
    end

    // State transition logic with reset
    always @(posedge clk or posedge reset) begin
        current_state <= next_state;

    end

    // Next state logic
    always @(*) begin
        if(reset == 1) begin
            next_state = S0;
        end else begin
            case (current_state)
                S0: next_state = (in_bit == 0) ? S1 : S0;
                S1: next_state = (in_bit == 1) ? S2 : S1;
                S2: next_state = (in_bit == 1) ? S3 : S1;
                S3: next_state = (in_bit == 0) ? S4 : S0;
                S4: next_state = (in_bit == 1) ? S5 : S1;
                S5: next_state = (in_bit == 1) ? S6 : S1;
                S6: next_state = (in_bit == 0) ? S7 : S0;
                S7: next_state = (in_bit == 0) ? S1 : S5;
                default: next_state = S0;
            endcase
        end
    end

    // Output logic
    always @(*) begin
        seq_detected = (current_state == S7); // Assert output when sequence is detected
    end

endmodule

problem5/sequence.detector.testbench.v
`include "sequence.detector.module.v"
`timescale 1ns/1ps

module sequence_detector_tb;

    reg clk;
    reg reset;
    reg in_bit;
    wire seq_detected;

    sequence_detector detector (
        .clk(clk),
        .reset(reset),
        .in_bit(in_bit),
        .seq_detected(seq_detected)
    );

    // Clock generation: Toggle clock every 5 time units
    initial begin
        clk = 0;
        forever #5 clk = ~clk;
    end

    initial begin
        $dumpfile("waveform_problem5.vcd"); 
        $dumpvars(0, sequence_detector_tb); 
        in_bit = 0;
        reset = 1;
        #10 reset = 0;   // Deassert reset after 10 time units
        
        in_bit = 0;      // S0 -> S1
        #10;
        in_bit = 1;      // S1 -> S2
        #10;
        in_bit = 1;      // S2 -> S3
        #10;
        in_bit = 0;      // S3 -> S4
        #10;
        in_bit = 1;      // S4 -> S5
        #10;
        in_bit = 1;      // S5 -> S6
        #10;
        in_bit = 0;      // S6 -> S7
        #10;
        in_bit = 1;      // S7 -> S5 seq detector is one
        #10;
        in_bit = 0;      // S5 -> S1
        #10

        $finish;
    end

    // Monitor signals
    always @(posedge clk) begin
        $display("Time: %0t | reset: %b | in_bit: %b | Current State: %b | Next State: %b | seq_detected: %b",
                 $time, reset, in_bit, detector.current_state, detector.next_state, seq_detected);
    end

endmodule

problem5/waveform_problem5.vcd
$date
	Wed Jan 29 21:12:10 2025
$end
$version
	Icarus Verilog
$end
$timescale
	1ps
$end
$scope module sequence_detector_tb $end
$var wire 1 ! seq_detected $end
$var reg 1 " clk $end
$var reg 1 # in_bit $end
$var reg 1 $ reset $end
$scope module detector $end
$var wire 1 " clk $end
$var wire 1 # in_bit $end
$var wire 1 $ reset $end
$var reg 3 % current_state [2:0] $end
$var reg 3 & next_state [2:0] $end
$var reg 1 ! seq_detected $end
$upscope $end
$upscope $end
$enddefinitions $end
#0
$dumpvars
b0 &
b0 %
1$
0#
0"
0!
$end
#5000
1"
#10000
b1 &
0"
0$
#15000
b1 %
1"
#20000
b10 &
0"
1#
#25000
b11 &
b10 %
1"
#30000
0"
#35000
b0 &
b11 %
1"
#40000
b100 &
0"
0#
#45000
b1 &
b100 %
1"
#50000
b101 &
0"
1#
#55000
b110 &
b101 %
1"
#60000
0"
#65000
b0 &
b110 %
1"
#70000
b111 &
0"
0#
#75000
1!
b1 &
b111 %
1"
#80000
b101 &
0"
1#
#85000
0!
b110 &
b101 %
1"
#90000
b1 &
0"
0#
#95000
b1 %
1"
