problem4/Foroutan.Nazanin.402243084.problem4.module.v
module odd_counter (
    input wire clk,
    input wire reset, // Add reset input
    output reg [3:0] count
);

always @(posedge clk or posedge reset) begin
    if (reset) begin
        count <= 4'b0001; // Reset to 1
    end else begin
        case (count)
            4'b0001: count <= 4'b0011;
            4'b0011: count <= 4'b0101;
            4'b0101: count <= 4'b0111;
            4'b0111: count <= 4'b1001;
            4'b1001: count <= 4'b0001;
            default: count <= 4'b0001; // Default to 1
        endcase
    end
end

endmodule

problem4/Foroutan.Nazanin.402243084.problem4.testbench.v
`include "Foroutan.Nazanin.402243084.problem4.module.v"

module odd_counter_tb;

reg clk;
reg reset; // Add reset signal
wire [3:0] count;

// Instantiate the odd_counter module
odd_counter counter(
    .clk(clk),
    .reset(reset), // Connect reset signal
    .count(count)
);

// Clock generation
initial begin
    clk = 0;
    forever #5 clk = ~clk; // Toggle clock every 5 time units
end

initial begin
    $dumpfile("odd_counter_tb.vcd"); // Set the VCD file name
    $dumpvars(0, odd_counter_tb); 
    $monitor("Time = %0t, Count = %0d, Reset = %0d", $time, count, reset);

    // Initial reset
    reset = 1; // Apply reset
    #10;
    reset = 0; // Release reset

    // Wait for count to be 5
    wait (count == 4'b0101);
    reset = 1;
    #10;
    reset = 0;

    #100; // Run for additional 100 time units

    $finish;
end

endmodule

problem4/odd_counter_tb.vcd
$date
	Tue Jan 28 11:45:15 2025
$end
$version
	Icarus Verilog
$end
$timescale
	1s
$end
$scope module odd_counter_tb $end
$var wire 4 ! count [3:0] $end
$var reg 1 " clk $end
$var reg 1 # reset $end
$scope module counter $end
$var wire 1 " clk $end
$var wire 1 # reset $end
$var reg 4 $ count [3:0] $end
$upscope $end
$upscope $end
$enddefinitions $end
#0
$dumpvars
b1 $
1#
0"
b1 !
$end
#5
1"
#10
0"
0#
#15
b11 !
b11 $
1"
#20
0"
#25
1#
b1 !
b1 $
1"
#30
0"
#35
b11 !
b11 $
1"
0#
#40
0"
#45
b101 !
b101 $
1"
#50
0"
#55
b111 !
b111 $
1"
#60
0"
#65
b1001 !
b1001 $
1"
#70
0"
#75
b1 !
b1 $
1"
#80
0"
#85
b11 !
b11 $
1"
#90
0"
#95
b101 !
b101 $
1"
#100
0"
#105
b111 !
b111 $
1"
#110
0"
#115
b1001 !
b1001 $
1"
#120
0"
#125
b1 !
b1 $
1"
#130
0"
#135
b11 !
b11 $
1"
