problem1/Foroutan.Nazanin.402243084.problem1.module.v
module fun(input a, a_not, b, b_not, c, c_not, d, d_not, output out);

    wire w1, w2, w3, w4, w5, w6, w7;
    supply1 vdd;
    supply0 gnd;

    pmos(w1, vdd, a);
    pmos(out, w1, d);
    pmos(w2, vdd, b_not);
    pmos(out, w2, d);
    pmos(w3, vdd, a);
    pmos(out, w3, c_not);
    pmos(w4, vdd, b);
    pmos(out, w4, c_not);

    nmos(out, w5, a);
    nmos(out, w5, d);
    nmos(w5, w6, b_not);
    nmos(w5, w6, d);
    nmos(w6, w7, a);
    nmos(w6, w7, c_not);
    nmos(w7, gnd, b);
    nmos(w7, gnd, c_not);

endmodule

problem1/Foroutan.Nazanin.402243084.problem1.testbench.v
`include "Foroutan.Nazanin.402243084.problem1.module.v"

module problem1_TestBench();

    reg a, not_a, b, not_b, c, not_c, d, not_d;
    wire out;
    fun fun1(a, not_a, b, not_b, c, not_c, d, not_d, out);

    initial begin

        $dumpfile("waveform_problem1.vcd"); 
        $dumpvars(0, problem1_TestBench);

          
        a = 0;
        b = 0; 
        c = 0; 
        d = 0; 
        not_a = ~a;
        not_b = ~b;
        not_d = ~d;
        not_c = ~c;
        $display("A:%d , B:%d , C:%d , D:%d --> %d",a,b,c,d, out);

        #1;  
        a = 0;
        b = 0; 
        c = 0; 
        d = 1; 
        not_a = ~a;
        not_b = ~b;
        not_d = ~d;
        not_c = ~c;
        $display("A:%d , B:%d , C:%d , D:%d --> %d",a,b,c,d, out);

        #1;  
        a = 0;
        b = 0; 
        c = 1; 
        d = 0; 
        not_a = ~a;
        not_b = ~b;
        not_d = ~d;
        not_c = ~c;
        $display("A:%d , B:%d , C:%d , D:%d --> %d",a,b,c,d, out);

        #1;  
        a = 0;
        b = 0; 
        c = 1; 
        d = 1; 
        not_a = ~a;
        not_b = ~b;
        not_d = ~d;
        not_c = ~c;
        $display("A:%d , B:%d , C:%d , D:%d --> %d",a,b,c,d, out);

        #1;  
        a = 0;
        b = 1; 
        c = 0; 
        d = 0; 
        not_a = ~a;
        not_b = ~b;
        not_d = ~d;
        not_c = ~c;
        $display("A:%d , B:%d , C:%d , D:%d --> %d",a,b,c,d, out);

        #1;  
        a = 0;
        b = 1; 
        c = 0; 
        d = 1; 
        not_a = ~a;
        not_b = ~b;
        not_d = ~d;
        not_c = ~c;
        $display("A:%d , B:%d , C:%d , D:%d --> %d",a,b,c,d, out);

        #1;  
        a = 0;
        b = 1; 
        c = 1; 
        d = 0; 
        not_a = ~a;
        not_b = ~b;
        not_d = ~d;
        not_c = ~c;
        $display("A:%d , B:%d , C:%d , D:%d --> %d",a,b,c,d, out);

        #1;  
        a = 0;
        b = 1; 
        c = 1; 
        d = 1; 
        not_a = ~a;
        not_b = ~b;
        not_d = ~d;
        not_c = ~c;
        $display("A:%d , B:%d , C:%d , D:%d --> %d",a,b,c,d, out);

        #1;  
        a = 1;
        b = 0; 
        c = 0; 
        d = 0; 
        not_a = ~a;
        not_b = ~b;
        not_d = ~d;
        not_c = ~c;
        $display("A:%d , B:%d , C:%d , D:%d --> %d",a,b,c,d, out);

        #1;  
        a = 1;
        b = 0; 
        c = 0; 
        d = 1; 
        not_a = ~a;
        not_b = ~b;
        not_d = ~d;
        not_c = ~c;
        $display("A:%d , B:%d , C:%d , D:%d --> %d",a,b,c,d, out);

        #1;  
        a = 1;
        b = 0; 
        c = 1; 
        d = 0; 
        not_a = ~a;
        not_b = ~b;
        not_d = ~d;
        not_c = ~c;
        $display("A:%d , B:%d , C:%d , D:%d --> %d",a,b,c,d, out);

        #1;  
        a = 1;
        b = 0; 
        c = 1; 
        d = 1; 
        not_a = ~a;
        not_b = ~b;
        not_d = ~d;
        not_c = ~c;
        $display("A:%d , B:%d , C:%d , D:%d --> %d",a,b,c,d, out);

        #1;  
        a = 1;
        b = 1; 
        c = 0; 
        d = 0; 
        not_a = ~a;
        not_b = ~b;
        not_d = ~d;
        not_c = ~c;
        $display("A:%d , B:%d , C:%d , D:%d --> %d",a,b,c,d, out);

        #1;  
        a = 1;
        b = 1; 
        c = 0; 
        d = 1; 
        not_a = ~a;
        not_b = ~b;
        not_d = ~d;
        not_c = ~c;
        $display("A:%d , B:%d , C:%d , D:%d --> %d",a,b,c,d, out);

        #1;  
        a = 1;
        b = 1; 
        c = 1; 
        d = 0; 
        not_a = ~a;
        not_b = ~b;
        not_d = ~d;
        not_c = ~c;
        $display("A:%d , B:%d , C:%d , D:%d --> %d",a,b,c,d, out);

        #1;  
        a = 1;
        b = 1; 
        c = 1; 
        d = 1; 
        not_a = ~a;
        not_b = ~b;
        not_d = ~d;
        not_c = ~c;
        $display("A:%d , B:%d , C:%d , D:%d --> %d",a,b,c,d, out);

    end
endmodule

problem1/waveform_problem1.vcd
$date
	Tue Jan 28 10:24:05 2025
$end
$version
	Icarus Verilog
$end
$timescale
	1s
$end
$scope module problem1_TestBench $end
$var wire 1 ! out $end
$var reg 1 " a $end
$var reg 1 # b $end
$var reg 1 $ c $end
$var reg 1 % d $end
$var reg 1 & not_a $end
$var reg 1 ' not_b $end
$var reg 1 ( not_c $end
$var reg 1 ) not_d $end
$scope module fun1 $end
$var wire 1 " a $end
$var wire 1 & a_not $end
$var wire 1 # b $end
$var wire 1 ' b_not $end
$var wire 1 $ c $end
$var wire 1 ( c_not $end
$var wire 1 % d $end
$var wire 1 ) d_not $end
$var wire 1 * gnd $end
$var wire 1 ! out $end
$var wire 1 + vdd $end
$var wire 1 , w1 $end
$var wire 1 - w2 $end
$var wire 1 . w3 $end
$var wire 1 / w4 $end
$var wire 1 0 w5 $end
$var wire 1 1 w6 $end
$var wire 1 2 w7 $end
$upscope $end
$upscope $end
$enddefinitions $end
#0
$dumpvars
02
01
00
1/
1.
z-
1,
1+
0*
1)
1(
1'
1&
0%
0$
0#
0"
1!
$end
#1
0)
0!
1%
#2
z0
z1
z2
0(
1)
1!
0%
1$
#3
0)
1%
#4
01
1(
1)
1-
0'
0%
0$
z/
02
1#
#5
0)
0!
00
1%
#6
z1
0(
1)
1!
z0
0%
1$
#7
0)
1%
#8
1(
1)
z-
1'
0&
0%
0$
1/
02
0#
z,
z.
0!
00
01
1"
#9
0)
1%
#10
1!
z0
z1
z2
0(
1)
0%
1$
#11
0)
1%
#12
1(
1)
1-
0'
0%
0$
z/
1!
z0
01
02
1#
#13
0)
0!
00
1%
#14
0(
1)
1!
z0
0%
1$
#15
0)
0!
00
1%
